traderclient/__init__.py
traderclient/cli.py
traderclient/client.py
traderclient/datatypes.py
traderclient/demo.py
traderclient/transport.py
traderclient/utils.py
zillionare_trader_client-0.4.4.dist-info/LICENSE
zillionare_trader_client-0.4.4.dist-info/METADATA
zillionare_trader_client-0.4.4.dist-info/WHEEL
zillionare_trader_client-0.4.4.dist-info/entry_points.txt
zillionare_trader_client-0.4.4.dist-info/RECORD
