Metadata-Version: 2.1
Name: zillionare-trader-client
Version: 0.4.4
Summary: Zillionare Trader Client
Home-page: https://github.com/zillionare/trader-client
License: MIT
Author: Aaron Yang
Author-email: code@jieyu.ai
Requires-Python: >=3.8,<3.9
Classifier: Development Status :: 2 - Pre-Alpha
Classifier: Intended Audience :: Developers
Classifier: License :: OSI Approved :: MIT License
Classifier: Natural Language :: English
Classifier: Programming Language :: Python :: 3
Classifier: Programming Language :: Python :: 3.8
Classifier: Programming Language :: Python :: 3.8
Provides-Extra: dev
Provides-Extra: doc
Provides-Extra: test
Requires-Dist: arrow (>=1.2.3,<2.0.0)
Requires-Dist: black (>=22.3.0,<23.0.0) ; extra == "test"
Requires-Dist: flake8 (==3.8.4) ; extra == "test"
Requires-Dist: flake8-docstrings (>=1.6.0,<2.0.0) ; extra == "test"
Requires-Dist: httpx (>=0.23,<0.24)
Requires-Dist: isort (==5.6.4) ; extra == "test"
Requires-Dist: livereload (>=2.6.3,<3.0.0) ; extra == "doc"
Requires-Dist: mike (>=1.1.2,<2.0.0) ; extra == "doc"
Requires-Dist: mkdocs (>=1.2.3,<2.0.0) ; extra == "doc"
Requires-Dist: mkdocs-autorefs (>=0.4.1,<0.5.0) ; extra == "doc"
Requires-Dist: mkdocs-include-markdown-plugin (>=3.2.3,<4.0.0) ; extra == "doc"
Requires-Dist: mkdocs-material (>=8.1.11,<9.0.0) ; extra == "doc"
Requires-Dist: mkdocs-material-extensions (>=1.0.3,<2.0.0)
Requires-Dist: mkdocstrings (>=0.18.0,<0.19.0) ; extra == "doc"
Requires-Dist: numpy (>=1.24.3,<2.0.0)
Requires-Dist: pre-commit (>=2.12.0,<3.0.0) ; extra == "dev"
Requires-Dist: pytest-cov (==2.10.1) ; extra == "test"
Requires-Dist: sanic (>=23.3.0,<24.0.0) ; extra == "test"
Requires-Dist: toml (>=0.10.2,<0.11.0) ; extra == "dev"
Requires-Dist: tox (>=3.20.1,<4.0.0) ; extra == "dev"
Requires-Dist: twine (>=3.3.0,<4.0.0) ; extra == "dev"
Requires-Dist: zillionare-core-types (>=0.6,<0.7)
